MANIFEST.in
README.md
VERSION
setup.cfg
setup.py
nefertari/__init__.py
nefertari/acl.py
nefertari/elasticsearch.py
nefertari/engine.py
nefertari/events.py
nefertari/json_httpexceptions.py
nefertari/logstash.py
nefertari/polymorphic.py
nefertari/renderers.py
nefertari/resource.py
nefertari/tweens.py
nefertari/view.py
nefertari/view_helpers.py
nefertari/wrappers.py
nefertari.egg-info/PKG-INFO
nefertari.egg-info/SOURCES.txt
nefertari.egg-info/dependency_links.txt
nefertari.egg-info/entry_points.txt
nefertari.egg-info/not-zip-safe
nefertari.egg-info/pbr.json
nefertari.egg-info/requires.txt
nefertari.egg-info/top_level.txt
nefertari/authentication/__init__.py
nefertari/authentication/models.py
nefertari/authentication/policies.py
nefertari/authentication/views.py
nefertari/scaffolds/__init__.py
nefertari/scaffolds/__init__.pyc
nefertari/scaffolds/__pycache__/__init__.cpython-33.pyc
nefertari/scaffolds/__pycache__/__init__.cpython-34.pyc
nefertari/scaffolds/__pycache__/__init__.cpython-35.pyc
nefertari/scaffolds/nefertari_starter/MANIFEST.in_tmpl
nefertari/scaffolds/nefertari_starter/README.md
nefertari/scaffolds/nefertari_starter/local.ini_tmpl
nefertari/scaffolds/nefertari_starter/requirements.txt
nefertari/scaffolds/nefertari_starter/setup.py_tmpl
nefertari/scaffolds/nefertari_starter/+package+/__init__.py_tmpl
nefertari/scaffolds/nefertari_starter/+package+/models/__init__.py_tmpl
nefertari/scaffolds/nefertari_starter/+package+/models/item.py_tmpl
nefertari/scaffolds/nefertari_starter/+package+/tests/__init__.py
nefertari/scaffolds/nefertari_starter/+package+/tests/api.raml
nefertari/scaffolds/nefertari_starter/+package+/tests/items.json
nefertari/scaffolds/nefertari_starter/+package+/tests/requirements.txt
nefertari/scaffolds/nefertari_starter/+package+/tests/test_api.py_tmpl
nefertari/scaffolds/nefertari_starter/+package+/views/__init__.py
nefertari/scaffolds/nefertari_starter/+package+/views/items.py_tmpl
nefertari/scripts/__init__.py
nefertari/scripts/es.py
nefertari/scripts/post2api.py
nefertari/scripts/scaffold_test.py
nefertari/utils/__init__.py
nefertari/utils/data.py
nefertari/utils/dictset.py
nefertari/utils/utils.py