Metadata-Version: 1.1
Name: nefertari
Version: 0.7.0
Summary: REST API framework for Pyramid
Home-page: https://github.com/ramses-tech/nefertari
Author: Ramses
Author-email: hello@ramses.tech
License: UNKNOWN
Keywords: web wsgi bfg pylons pyramid rest api elasticsearch
Platform: UNKNOWN
Classifier: Programming Language :: Python
Classifier: Programming Language :: Python :: 2
Classifier: Programming Language :: Python :: 2.7
Classifier: Programming Language :: Python :: 3
Classifier: Programming Language :: Python :: 3.4
Classifier: Programming Language :: Python :: 3.5
Classifier: Framework :: Pyramid
Classifier: Topic :: Internet :: WWW/HTTP
Classifier: Topic :: Internet :: WWW/HTTP :: WSGI :: Application
